imageforllm/__init__.py
imageforllm/_hook.py
imageforllm/_metadata.py
imageforllm/ai_metadata.py
imageforllm/extract.py
imageforllm/examples/ai_metadata_example.py
imageforllm/examples/bytes_example.py
imageforllm/examples/saveandread.py
imageforllm-0.4.0.dist-info/licenses/LICENSE
imageforllm-0.4.0.dist-info/METADATA
imageforllm-0.4.0.dist-info/WHEEL
imageforllm-0.4.0.dist-info/entry_points.txt
imageforllm-0.4.0.dist-info/top_level.txt
imageforllm-0.4.0.dist-info/RECORD
