Metadata-Version: 2.4
Name: imageforllm
Version: 0.4.0
Summary: A library for embedding code and plot properties into matplotlib images for LLM context
Author-email: kexinoh <findmykexin@gmail.com>
Maintainer-email: kexinoh <findmykexin@gmail.com>
License: MIT License
Project-URL: Homepage, https://github.com/kexinoh/imageforllm
Project-URL: Bug Tracker, https://github.com/kexinoh/imageforllm/issues
Keywords: matplotlib,image,metadata,llm
Classifier: Programming Language :: Python :: 3
Classifier: License :: OSI Approved :: MIT License
Classifier: Operating System :: OS Independent
License-File: LICENSE
Dynamic: license-file
